toolmux/__init__.py
toolmux/main.py
toolmux/Prompt/AGENT_INSTRUCTIONS.md
toolmux/examples/brave-search.json
toolmux/examples/example_agent_config.json
toolmux/examples/example_mcp.json
toolmux/examples/filesystem.json
toolmux/examples/http-servers.json
toolmux/examples/kiro-integration.json
toolmux/examples/mixed-servers.json
toolmux/examples/q-cli-agent.json
toolmux/examples/q-cli-simple.json
toolmux/examples/sqlite.json
toolmux/scripts/toolmux_hook.sh
toolmux-1.2.1.dist-info/licenses/LICENSE
toolmux-1.2.1.dist-info/METADATA
toolmux-1.2.1.dist-info/WHEEL
toolmux-1.2.1.dist-info/entry_points.txt
toolmux-1.2.1.dist-info/top_level.txt
toolmux-1.2.1.dist-info/RECORD
