Metadata-Version: 2.4
Name: toolmux
Version: 1.2.1
Summary: Efficient MCP server aggregation with HTTP/SSE support and 98% schema token reduction
Author-email: JP Ruiz <juanpa.ruiz@gmail.com>
License-Expression: MIT
Project-URL: Homepage, https://github.com/subnetangel/ToolMux
Project-URL: Repository, https://github.com/subnetangel/ToolMux
Project-URL: Issues, https://github.com/subnetangel/ToolMux/issues
Keywords: mcp,model-context-protocol,multiplexer,aggregation,toolmux,ai,agents,tools
Classifier: Development Status :: 4 - Beta
Classifier: Intended Audience :: Developers
Classifier: Programming Language :: Python :: 3
Classifier: Programming Language :: Python :: 3.10
Classifier: Programming Language :: Python :: 3.11
Classifier: Programming Language :: Python :: 3.12
Classifier: Topic :: Software Development :: Libraries :: Python Modules
Classifier: Topic :: System :: Networking
Classifier: Topic :: Internet :: WWW/HTTP :: HTTP Servers
Classifier: Environment :: Console
Requires-Python: >=3.10
License-File: LICENSE
Requires-Dist: fastmcp>=0.2.0
Requires-Dist: click>=8.0.0
Requires-Dist: pydantic>=2.6.0
Requires-Dist: httpx>=0.24.0
Requires-Dist: websockets>=11.0.0
Requires-Dist: python-dotenv>=1.0.1
Provides-Extra: dev
Requires-Dist: pytest>=7.0.0; extra == "dev"
Requires-Dist: black>=23.0.0; extra == "dev"
Requires-Dist: ruff>=0.1.0; extra == "dev"
Requires-Dist: mypy>=1.0.0; extra == "dev"
Provides-Extra: server
Requires-Dist: fastapi>=0.104.0; extra == "server"
Requires-Dist: uvicorn>=0.24.0; extra == "server"
Dynamic: license-file
